markdown_image_replacer/__init__.py
markdown_image_replacer/__main__.py
markdown_image_replacer/replace_pictures.py
markdown_image_replacer-0.0.2.dist-info/METADATA
markdown_image_replacer-0.0.2.dist-info/WHEEL
markdown_image_replacer-0.0.2.dist-info/licenses/LICENSE
markdown_image_replacer-0.0.2.dist-info/RECORD
